[
  {
    "id": "MC-167108",
    "summary": "Lines on the debug screen are taller than before",
    "labels": [],
    "status": "Resolved",
    "confirmation_status": "Confirmed",
    "categories": [
      "Debug",
      "UI"
    ],
    "priority": "None",
    "fix_versions": [
      "1.15 Pre-release 7"
    ],
    "creation_date": "2019-12-04T22:23:16.000+0000",
    "resolution_date": "2019-12-09T11:32:45.000+0000",
    "updated_date": "2019-12-09T11:32:46.000+0000",
    "watches": 3,
    "votes": 4
  },
  {
    "id": "MC-167106",
    "summary": "Debug screen FPS / TPS graphs are not rendered correctly",
    "labels": [],
    "status": "Resolved",
    "confirmation_status": "Confirmed",
    "categories": [
      "Debug"
    ],
    "priority": "None",
    "fix_versions": [
      "1.15 Pre-release 7"
    ],
    "creation_date": "2019-12-04T21:24:42.000+0000",
    "resolution_date": "2019-12-09T11:32:39.000+0000",
    "updated_date": "2019-12-09T14:35:46.000+0000",
    "watches": 2,
    "votes": 3
  },
  {
    "id": "MC-167105",
    "summary": "Debug screen renders behind hotbar",
    "labels": [],
    "status": "Resolved",
    "confirmation_status": "Confirmed",
    "categories": [
      "Debug",
      "Rendering"
    ],
    "priority": "Important",
    "fix_versions": [
      "1.15 Pre-release 7"
    ],
    "creation_date": "2019-12-04T21:22:52.000+0000",
    "resolution_date": "2019-12-09T19:47:19.000+0000",
    "updated_date": "2019-12-09T19:47:20.000+0000",
    "watches": 4,
    "votes": 4
  },
  {
    "id": "MC-167061",
    "summary": "FPS/TPS graphs on F3 screen are empty in spectator mode",
    "labels": [],
    "status": "Resolved",
    "confirmation_status": "Confirmed",
    "categories": [
      "(Unassigned)"
    ],
    "priority": "None",
    "fix_versions": [
      "1.15 Pre-release 7"
    ],
    "creation_date": "2019-12-03T21:53:12.000+0000",
    "resolution_date": "2019-12-09T11:32:29.000+0000",
    "updated_date": "2020-02-05T22:46:48.000+0000",
    "watches": 2,
    "votes": 5
  }
]
