[
  {
    "id": "MC-268778",
    "summary": "Baby armadillos shouldn't drop scutes when brushed",
    "labels": [],
    "status": "Resolved",
    "confirmation_status": "Confirmed",
    "categories": [
      "Mob behaviour"
    ],
    "priority": "Normal",
    "fix_versions": [
      "24w09a"
    ],
    "creation_date": "2024-02-26T15:40:33.000+0200",
    "resolution_date": "2024-02-28T11:46:17.000+0200",
    "updated_date": "2024-02-28T11:46:17.000+0200",
    "watches": 4,
    "votes": 3
  },
  {
    "id": "MC-268710",
    "summary": "The fall damage reduction for the Wind Charge is not working",
    "labels": [
      "wind_charge"
    ],
    "status": "Resolved",
    "confirmation_status": "Confirmed",
    "categories": [
      "Items",
      "Player"
    ],
    "priority": "None",
    "fix_versions": [
      "24w09a"
    ],
    "creation_date": "2024-02-22T00:06:40.000+0200",
    "resolution_date": "2024-02-23T10:02:33.000+0200",
    "updated_date": "2024-02-23T10:02:33.000+0200",
    "watches": 5,
    "votes": 2
  },
  {
    "id": "MC-268580",
    "summary": "Chiseled bookshelf model is not deterministic in data generation",
    "labels": [],
    "status": "Resolved",
    "confirmation_status": "Confirmed",
    "categories": [
      "Data Packs",
      "Textures and models"
    ],
    "priority": "Low",
    "fix_versions": [
      "24w09a"
    ],
    "creation_date": "2024-02-14T23:54:16.000+0200",
    "resolution_date": "2024-02-15T17:18:34.000+0200",
    "updated_date": "2024-02-15T17:18:34.000+0200",
    "watches": 3,
    "votes": 2
  },
  {
    "id": "MC-268350",
    "summary": "Wind Charges never despawn",
    "labels": [
      "wind_charge"
    ],
    "status": "Resolved",
    "confirmation_status": "Confirmed",
    "categories": [
      "Entities"
    ],
    "priority": "Important",
    "fix_versions": [
      "24w09a"
    ],
    "creation_date": "2024-02-07T19:11:35.000+0200",
    "resolution_date": "2024-02-16T07:40:52.000+0200",
    "updated_date": "2024-02-16T07:40:52.000+0200",
    "watches": 6,
    "votes": 10
  },
  {
    "id": "MC-268236",
    "summary": "Search field in the social interactions menu not focused by default",
    "labels": [],
    "status": "Resolved",
    "confirmation_status": "Confirmed",
    "categories": [
      "Accessibility",
      "Social Interactions",
      "UI"
    ],
    "priority": "Low",
    "fix_versions": [
      "24w09a"
    ],
    "creation_date": "2024-02-02T17:12:43.000+0200",
    "resolution_date": "2024-02-28T11:57:55.000+0200",
    "updated_date": "2024-02-28T11:57:55.000+0200",
    "watches": 0,
    "votes": 0
  },
  {
    "id": "MC-268022",
    "summary": "Elements within the list in the \"Experimental feature requirements\" menu cannot be selected via the mouse cursor",
    "labels": [],
    "status": "Resolved",
    "confirmation_status": "Confirmed",
    "categories": [
      "Accessibility",
      "UI"
    ],
    "priority": "Important",
    "fix_versions": [
      "24w09a"
    ],
    "creation_date": "2024-01-21T17:01:40.000+0200",
    "resolution_date": "2024-02-28T11:57:55.000+0200",
    "updated_date": "2024-02-28T11:57:55.000+0200",
    "watches": 2,
    "votes": 2
  },
  {
    "id": "MC-268011",
    "summary": "Hoppers leak the last world they sucked item on",
    "labels": [],
    "status": "Resolved",
    "confirmation_status": "Plausible",
    "categories": [
      "Performance"
    ],
    "priority": "Normal",
    "fix_versions": [
      "24w09a"
    ],
    "creation_date": "2024-01-20T19:55:36.000+0200",
    "resolution_date": "2024-02-27T11:29:48.000+0200",
    "updated_date": "2024-02-27T11:29:48.000+0200",
    "watches": 3,
    "votes": 5
  },
  {
    "id": "MC-267976",
    "summary": "The scroll bar in the realms player list can no longer be dragged using the mouse cursor",
    "labels": [
      "realms"
    ],
    "status": "Resolved",
    "confirmation_status": "Confirmed",
    "categories": [
      "Accessibility",
      "UI"
    ],
    "priority": "Normal",
    "fix_versions": [
      "24w09a"
    ],
    "creation_date": "2024-01-19T14:16:59.000+0200",
    "resolution_date": "2024-02-28T11:57:56.000+0200",
    "updated_date": "2024-02-28T11:57:56.000+0200",
    "watches": 2,
    "votes": 1
  },
  {
    "id": "MC-267975",
    "summary": "The realms player list is rendered larger than its visual size",
    "labels": [
      "realms"
    ],
    "status": "Resolved",
    "confirmation_status": "Confirmed",
    "categories": [
      "Rendering",
      "UI"
    ],
    "priority": "Normal",
    "fix_versions": [
      "24w09a"
    ],
    "creation_date": "2024-01-19T14:12:53.000+0200",
    "resolution_date": "2024-02-28T11:57:56.000+0200",
    "updated_date": "2024-02-28T11:57:56.000+0200",
    "watches": 2,
    "votes": 1
  },
  {
    "id": "MC-267956",
    "summary": "Attack indicator is not displayed when holding a Diamond or Netherite Hoe",
    "labels": [],
    "status": "Resolved",
    "confirmation_status": "Confirmed",
    "categories": [
      "Player"
    ],
    "priority": "Normal",
    "fix_versions": [
      "24w09a"
    ],
    "creation_date": "2024-01-18T19:08:38.000+0200",
    "resolution_date": "2024-02-28T18:17:19.000+0200",
    "updated_date": "2024-02-28T18:17:19.000+0200",
    "watches": 4,
    "votes": 6
  },
  {
    "id": "MC-267500",
    "summary": "Attribute modifier on an item with the first and/or last 2 integers of the UUID being 0 are non-functional",
    "labels": [],
    "status": "Resolved",
    "confirmation_status": "Confirmed",
    "categories": [
      "Commands"
    ],
    "priority": "Normal",
    "fix_versions": [
      "24w09a"
    ],
    "creation_date": "2023-12-21T18:32:29.000+0200",
    "resolution_date": "2024-02-27T11:29:46.000+0200",
    "updated_date": "2024-02-27T11:29:46.000+0200",
    "watches": 3,
    "votes": 3
  },
  {
    "id": "MC-267451",
    "summary": "Items named with an anvil on 1.20.4 don't stack with items named prior",
    "labels": [],
    "status": "Resolved",
    "confirmation_status": "Confirmed",
    "categories": [
      "Datafixer"
    ],
    "priority": "Normal",
    "fix_versions": [
      "24w09a"
    ],
    "creation_date": "2023-12-19T19:33:37.000+0200",
    "resolution_date": "2024-02-27T11:38:12.000+0200",
    "updated_date": "2024-02-27T11:38:12.000+0200",
    "watches": 4,
    "votes": 3
  },
  {
    "id": "MC-257119",
    "summary": "Lodestone Compass does not stack after dropping and destroying the Lodestone",
    "labels": [],
    "status": "Resolved",
    "confirmation_status": "Confirmed",
    "categories": [],
    "priority": "Low",
    "fix_versions": [
      "24w09a"
    ],
    "creation_date": "2022-11-02T18:47:29.000+0200",
    "resolution_date": "2024-02-27T11:29:47.000+0200",
    "updated_date": "2024-02-27T11:29:47.000+0200",
    "watches": 4,
    "votes": 2
  },
  {
    "id": "MC-251042",
    "summary": "Third-party warning buttons are not positioned well in non-English languages",
    "labels": [],
    "status": "Resolved",
    "confirmation_status": "Confirmed",
    "categories": [
      "UI"
    ],
    "priority": "Normal",
    "fix_versions": [
      "24w09a"
    ],
    "creation_date": "2022-04-28T16:48:39.000+0300",
    "resolution_date": "2024-02-28T11:57:57.000+0200",
    "updated_date": "2024-02-28T11:57:57.000+0200",
    "watches": 2,
    "votes": 1
  },
  {
    "id": "MC-226775",
    "summary": "Extinguishing candle shows inaccurate subtitle",
    "labels": [
      "candle"
    ],
    "status": "Resolved",
    "confirmation_status": "Confirmed",
    "categories": [
      "Accessibility",
      "Text"
    ],
    "priority": "Low",
    "fix_versions": [
      "24w09a"
    ],
    "creation_date": "2021-05-30T00:23:18.000+0300",
    "resolution_date": "2024-02-22T10:45:13.000+0200",
    "updated_date": "2024-02-22T10:45:13.000+0200",
    "watches": 1,
    "votes": 6
  },
  {
    "id": "MC-195572",
    "summary": "The fog from lava is much denser when having the Fire Resistance effect active compared to Bedrock Edition",
    "labels": [
      "vanilla-parity"
    ],
    "status": "Resolved",
    "confirmation_status": "Confirmed",
    "categories": [
      "Parity"
    ],
    "priority": "Normal",
    "fix_versions": [
      "24w09a"
    ],
    "creation_date": "2020-07-20T17:36:26.000+0300",
    "resolution_date": "2024-02-22T10:53:29.000+0200",
    "updated_date": "2024-02-22T10:53:29.000+0200",
    "watches": 7,
    "votes": 34
  },
  {
    "id": "MC-148480",
    "summary": "Putting two identical enchanted books in a grindstone will output one book",
    "labels": [
      "enchanted_book",
      "grindstone"
    ],
    "status": "Resolved",
    "confirmation_status": "Confirmed",
    "categories": [
      "Items",
      "UI"
    ],
    "priority": "None",
    "fix_versions": [
      "24w09a"
    ],
    "creation_date": "2019-04-17T02:56:23.000+0300",
    "resolution_date": "2024-02-29T11:50:37.000+0200",
    "updated_date": "2024-02-29T11:50:37.000+0200",
    "watches": 4,
    "votes": 8
  },
  {
    "id": "MC-118890",
    "summary": "Tipped arrows stuck in the ground never lose their effect",
    "labels": [
      "CustomPotionEffects",
      "effect",
      "inGround",
      "tipped_arrow"
    ],
    "status": "Resolved",
    "confirmation_status": "Confirmed",
    "categories": [
      "(Unassigned)"
    ],
    "priority": "None",
    "fix_versions": [
      "24w09a"
    ],
    "creation_date": "2017-06-22T18:14:24.000+0300",
    "resolution_date": "2024-02-27T11:29:46.000+0200",
    "updated_date": "2024-02-27T11:29:46.000+0200",
    "watches": 3,
    "votes": 7
  },
  {
    "id": "MC-100016",
    "summary": "Singleplayer world selection screen is shown incorrectly when light_dirt_background.png and/or options_background.png are transparent",
    "labels": [
      "GUI",
      "resource-pack-support",
      "transparency"
    ],
    "status": "Resolved",
    "confirmation_status": "Confirmed",
    "categories": [
      "UI"
    ],
    "priority": "None",
    "fix_versions": [
      "24w09a"
    ],
    "creation_date": "2016-03-24T12:55:08.000+0200",
    "resolution_date": "2024-02-29T00:47:30.000+0200",
    "updated_date": "2024-02-29T00:47:30.000+0200",
    "watches": 7,
    "votes": 8
  },
  {
    "id": "MC-19893",
    "summary": "options_background.png is incorrectly displayed upside down in the credits after beating the dragon",
    "labels": [
      "background",
      "credits",
      "upside-down"
    ],
    "status": "Resolved",
    "confirmation_status": "Confirmed",
    "categories": [
      "Textures and models",
      "UI"
    ],
    "priority": "Low",
    "fix_versions": [
      "24w09a"
    ],
    "creation_date": "2013-06-30T15:29:29.000+0300",
    "resolution_date": "2024-02-28T18:18:12.000+0200",
    "updated_date": "2024-02-28T20:27:47.000+0200",
    "watches": 11,
    "votes": 13
  }
]
